MANIFEST.in
README.md
setup.py
lib/__init__.py
lib/storj_env.py
lib/ext/__init__.py
lib/ext/python_libstorj.cpp
lib/ext/python_libstorj.h
lib/ext/python_libstorj.py
lib/ext/python_libstorj_wrap.cxx
lib/ext/upload_options.py
python_libstorj.egg-info/PKG-INFO
python_libstorj.egg-info/SOURCES.txt
python_libstorj.egg-info/dependency_links.txt
python_libstorj.egg-info/requires.txt
python_libstorj.egg-info/top_level.txt