Metadata-Version: 1.0
Name: python-libstorj
Version: 1.0a2
Summary: Python bindings for [libstorj](https://github.com/storj/libstorj)
Home-page: https://github.com/storj/python-libstorj
Author: Bryan White
Author-email: bryanchriswhite@gmail.com
License: UNKNOWN
Platform: UNKNOWN
